LICENSE
MANIFEST.in
README.md
requirements.txt
setup.cfg
setup.py
gcdt_gen_serverless/__init__.py
gcdt_gen_serverless/generator.py
gcdt_gen_serverless/scaffold.py
gcdt_gen_serverless/swagger.py
gcdt_gen_serverless.egg-info/PKG-INFO
gcdt_gen_serverless.egg-info/SOURCES.txt
gcdt_gen_serverless.egg-info/dependency_links.txt
gcdt_gen_serverless.egg-info/entry_points.txt
gcdt_gen_serverless.egg-info/requires.txt
gcdt_gen_serverless.egg-info/top_level.txt