Metadata-Version: 1.1
Name: gcdt-gen-serverless
Version: 0.0.5
Summary: Serverless generator for gcdt
Home-page: UNKNOWN
Author: glomex OPS Team
Author-email: mark.fink@glomex.com
License: MIT
Platform: UNKNOWN
Classifier: Development Status :: 3 - Alpha
Classifier: Intended Audience :: Developers
Classifier: Programming Language :: Python :: 2.7
